MANIFEST.in
setup.py
systemdunitextras/__init__.py
systemdunitextras/fail_handler.py
systemdunitextras/settings.py
systemdunitextras/watchdog_ping.py
systemdunitextras.egg-info/PKG-INFO
systemdunitextras.egg-info/SOURCES.txt
systemdunitextras.egg-info/dependency_links.txt
systemdunitextras.egg-info/entry_points.txt
systemdunitextras.egg-info/requires.txt
systemdunitextras.egg-info/top_level.txt
systemdunitextras/data/etc/systemd/system/systemd_fail_handler@.service