Metadata-Version: 1.0
Name: systemdunitextras
Version: 0.2.0
Summary: Provides watchdog_ping python module and a systemd unit fail handler, allowing to limit                  a notification for an OnFailure event of a specific systemd unit to a specified time span.
Home-page: UNKNOWN
Author: eayin2
Author-email: eayin2 at gmail dot com
License: UNKNOWN
Platform: UNKNOWN
